Workbook

Sheet Task1 
A3: Row Labels | B3: Sum of Net_Sales
A4: Beauty | B4: 296457.5
A5: Ahmedabad | B5: 18505
A6: Bangalore | B6: 23740
A7: Chennai | B7: 35592.5
A8: Delhi | B8: 44032.5
A9: Hyderabad | B9: 49557.5
A10: Kolkata | B10: 46880
A11: Mumbai | B11: 28172.5
A12: Pune | B12: 49977.5
A13: Books | B13: 175576.8
A14: Ahmedabad | B14: 16484.5
A15: Bangalore | B15: 14035.7
... A67: Grand Total | B67: 13896024

Sheet RetailSales_Dataset
A1: Order_ID | B1: Order_Date | C1: Customer_ID | D1: Customer_Name | E1: City | F1: Category | G1: Product_Name | H1: Quantity | I1: Unit_Price | J1: Discount_Pct | K1: Discount_Amt | L1: Net_Sales | M1: Profit | N1: Payment_Mode | O1: Delivery_Status | P1: Order_type | Q1: Order_Segment | R1: IFS
A2: ORD0001 | B2: 45254 | C2: CUST1377 | D2: Diya Mishra | E2: Mumbai | F2: Electronics | G2: Smartphone | H2: 3 | I2: 18000 | J2: 5 | K2: 2700 | L2: 51300 | M2: 6000.21 | N2: Net Banking | O2: Returned | P2: =IF(L2>20000,"High Value","Low Value") -> High Value | Q2: =IF(L2>50000,"Premium",IF(L2>20000,"High",IF(L2>5000,"Medium","Low"))) -> Premium | R2: {=_xlfn.IFS(L2>50000,"Premium",L2>20000,"High",L2>5000,"Medium",TRUE,"Low")} -> Premium
A3: ORD0002 | B3: 44943 | C3: CUST1013 | D3: Deepa Iyer | E3: Kolkata | F3: Electronics | G3: Smartphone | H3: 2 | I3: 18000 | J3: 5 | K3: 1800 | L3: 34200 | M3: 6894.95 | N3: Credit Card | O3: Returned | P3: =IF(L3>20000,"High Value","Low Value") -> High Value | Q3: =IF(L3>50000,"Premium",IF(L3>20000,"High",IF(L3>5000,"Medium","Low"))) -> High | R3: {=_xlfn.IFS(L3>50000,"Premium",L3>20000,"High",L3>5000,"Medium",TRUE,"Low")} -> High | S3: Net sales of Electronics | T3: =SUMIF(F2:F1001,"Electronics",L2:L1001) -> 7251440
A4: ORD0003 | B4: 45228 | C4: CUST1174 | D4: Rahul Reddy | E4: Chennai | F4: Groceries | G4: Coffee | H4: 1 | I4: 400 | J4: 5 | K4: 20 | L4: 380 | M4: 98.59 | N4: Debit Card | O4: Delivered | P4: =IF(L4>20000,"High Value","Low Value") -> Low Value | Q4: =IF(L4>50000,"Premium",IF(L4>20000,"High",IF(L4>5000,"Medium","Low"))) -> Low | R4: {=_xlfn.IFS(L4>50000,"Premium",L4>20000,"High",L4>5000,"Medium",TRUE,"Low")} -> Low | S4: Bangalore city net sales | T4: =SUMIF(E2:E1001,"Bangalore",L2:L1001) -> 2051852.9
A5: ORD0004 | B5: 44974 | C5: CUST1413 | D5: Vivaan Das | E5: Mumbai | F5: Furniture | G5: Office Chair | H5: 3 | I5: 8500 | J5: 10 | K5: 2550 | L5: 22950 | M5: 5304.15 | N5: Cash on Delivery | O5: Delivered | P5: =IF(L5>20000,"High Value","Low Value") -> High Value | Q5: =IF(L5>50000,"Premium",IF(L5>20000,"High",IF(L5>5000,"Medium","Low"))) -> High | R5: {=_xlfn.IFS(L5>50000,"Premium",L5>20000,"High",L5>5000,"Medium",TRUE,"Low")} -> High | S5: Total Profit for Sports | T5: =SUMIF(F2:F1001,"Sports",M2:M1001) -> 256334.91
A6: ORD0005 | B6: 45209 | C6: CUST1360 | D6: Ananya Verma | E6: Chennai | F6: Groceries | G6: Coffee | H6: 5 | I6: 400 | J6: 10 | K6: 200 | L6: 1800 | M6: 401.77 | N6: Debit Card | O6: Delivered | P6: =IF(L6>20000,"High Value","Low Value") -> Low Value | Q6: =IF(L6>50000,"Premium",IF(L6>20000,"High",IF(L6>5000,"Medium","Low"))) -> Low | R6: {=_xlfn.IFS(L6>50000,"Premium",L6>20000,"High",L6>5000,"Medium",TRUE,"Low")} -> Low | S6: Net_Sales for Delivered orders | T6: =SUMIF(O2:O1001,"Delivered",L2:L1001) -> 7695466
A7: ORD0006 | B7: 45046 | C7: CUST1427 | D7: Pooja Nair | E7: Pune | F7: Books | G7: Python Basics | H7: 4 | I7: 499 | J7: 10 | K7: 199.6 | L7: 1796.4 | M7: 334.17 | N7: Debit Card | O7: Delivered | P7: =IF(L7>20000,"High Value","Low Value") -> Low Value | Q7: =IF(L7>50000,"Premium",IF(L7>20000,"High",IF(L7>5000,"Medium","Low"))) -> Low | R7: {=_xlfn.IFS(L7>50000,"Premium",L7>20000,"High",L7>5000,"Medium",TRUE,"Low")} -> Low | S7: Net_Sales for Electronics in Bangalore | T7: =SUMIFS(L2:L1001,E2:E1001,"Bangalore",F2:F1001,"Electronics") -> 1080435
A8: ORD0007 | B8: 45270 | C8: CUST1273 | D8: Sneha Nair | E8: Ahmedabad | F8: Groceries | G8: Tea Powder | H8: 1 | I8: 250 | J8: 20 | K8: 50 | L8: 200 | M8: 48.1 | N8: Cash on Delivery | O8: Delivered | P8: =IF(L8>20000,"High Value","Low Value") -> Low Value | Q8: =IF(L8>50000,"Premium",IF(L8>20000,"High",IF(L8>5000,"Medium","Low"))) -> Low | R8: {=_xlfn.IFS(L8>50000,"Premium",L8>20000,"High",L8>5000,"Medium",TRUE,"Low")} -> Low | S8: Count of High value | T8: =COUNTIF(P2:P1001,"High Value") -> 150
A9: ORD0008 | B9: 45254 | C9: CUST1393 | D9: Vivaan Singh | E9: Bangalore | F9: Beauty | G9: Foundation | H9: 2 | I9: 850 | J9: 25 | K9: 425 | L9: 1275 | M9: 187.79 | N9: Debit Card | O9: Returned | P9: =IF(L9>20000,"High Value","Low Value") -> Low Value | Q9: =IF(L9>50000,"Premium",IF(L9>20000,"High",IF(L9>5000,"Medium","Low"))) -> Low | R9: {=_xlfn.IFS(L9>50000,"Premium",L9>20000,"High",L9>5000,"Medium",TRUE,"Low")} -> Low | S9: Count of Low value | T9: =COUNTIF(P1:P1001,"Low Value") -> 850
A10: ORD0009 | B10: 45064 | C10: CUST1335 | D10: Kavita Mehta | E10: Ahmedabad | F10: Electronics | G10: Laptop | H10: 5 | I10: 55000 | J10: 25 | K10: 68750 | L10: 206250 | M10: 29783.19 | N10: Credit Card | O10: Delivered | P10: =IF(L10>20000,"High Value","Low Value") -> High Value | Q10: =IF(L10>50000,"Premium",IF(L10>20000,"High",IF(L10>5000,"Medium","Low"))) -> Premium | R10: {=_xlfn.IFS(L10>50000,"Premium",L10>20000,"High",L10>5000,"Medium",TRUE,"Low")} -> Premium | S10: Premiun | T10: =COUNTIF(Q:Q,"Premium") -> 77
A11: ORD0010 | B11: 44998 | C11: CUST1299 | D11: Nisha Agarwal | E11: Kolkata | F11: Clothing | G11: Shoes | H11: 5 | I11: 2499 | J11: 20 | K11: 2499 | L11: 9996 | M11: 1287.71 | N11: Debit Card | O11: Delivered | P11: =IF(L11>20000,"High Value","Low Value") -> Low Value | Q11: =IF(L11>50000,"Premium",IF(L11>20000,"High",IF(L11>5000,"Medium","Low"))) -> Medium | R11: {=_xlfn.IFS(L11>50000,"Premium",L11>20000,"High",L11>5000,"Medium",TRUE,"Low")} -> Medium | S11: High | T11: =COUNTIF(Q:Q,"High") -> 73
A12: ORD0011 | B12: 44997 | C12: CUST1078 | D12: Priya Pillai | E12: Mumbai | F12: Sports | G12: Dumbbells | H12: 1 | I12: 2200 | J12: 0 | K12: 0 | L12: 2200 | M12: 678.33 | N12: Cash on Delivery | O12: Returned | P12: =IF(L12>20000,"High Value","Low Value") -> Low Value | Q12: =IF(L12>50000,"Premium",IF(L12>20000,"High",IF(L12>5000,"Medium","Low"))) -> Low | R12: {=_xlfn.IFS(L12>50000,"Premium",L12>20000,"High",L12>5000,"Medium",TRUE,"Low")} -> Low | S12: Medium | T12: =COUNTIF(Q:Q,"Medium") -> 242
A13: ORD0012 | B13: 45232 | C13: CUST1005 | D13: Diya Mishra | E13: Hyderabad | F13: Furniture | G13: Sofa | H13: 3 | I13: 25000 | J13: 20 | K13: 15000 | L13: 60000 | M13: 18494.03 | N13: Debit Card | O13: Delivered | P13: =IF(L13>20000,"High Value","Low Value") -> High Value | Q13: =IF(L13>50000,"Premium",IF(L13>20000,"High",IF(L13>5000,"Medium","Low"))) -> Premium | R13: {=_xlfn.IFS(L13>50000,"Premium",L13>20000,"High",L13>5000,"Medium",TRUE,"Low")} -> Premium | S13: Low | T13: =COUNTIF(Q:Q,"Low") -> 608
A14: ORD0013 | B14: 45077 | C14: CUST1448 | D14: Rahul Tiwari | E14: Delhi | F14: Furniture | G14: Study Table | H14: 4 | I14: 6500 | J14: 0 | K14: 0 | L14: 26000 | M14: 8739.76 | N14: Net Banking | O14: Delivered | P14: =IF(L14>20000,"High Value","Low Value") -> High Value | Q14: =IF(L14>50000,"Premium",IF(L14>20000,"High",IF(L14>5000,"Medium","Low"))) -> High | R14: {=_xlfn.IFS(L14>50000,"Premium",L14>20000,"High",L14>5000,"Medium",TRUE,"Low")} -> High
A15: ORD0014 | B15: 45247 | C15: CUST1191 | D15: Priya Mishra | E15: Bangalore | F15: Groceries | G15: Coffee | H15: 5 | I15: 400 | J15: 20 | K15: 400 | L15: 1600 | M15: 175.48 | N15: Net Banking | O15: Delivered | P15: =IF(L15>20000,"High Value","Low Value") -> Low Value | Q15: =IF(L15>50000,"Premium",IF(L15>20000,"High",IF(L15>5000,"Medium","Low"))) -> Low | R15: {=_xlfn.IFS(L15>50000,"Premium",L15>20000,"High",L15>5000,"Medium",TRUE,"Low")} -> Low
A16: ORD0015 | B16: 45177 | C16: CUST1123 | D16: Manish Patel | E16: Mumbai | F16: Electronics | G16: Smartphone | H16: 3 | I16: 18000 | J16: 10 | K16: 5400 | L16: 48600 | M16: 5921.21 | N16: Cash on Delivery | O16: Delivered | P16: =IF(L16>20000,"High Value","Low Value") -> High Value | Q16: =IF(L16>50000,"Premium",IF(L16>20000,"High",IF(L16>5000,"Medium","Low"))) -> High | R16: {=_xlfn.IFS(L16>50000,"Premium",L16>20000,"High",L16>5000,"Medium",TRUE,"Low")} -> High
A17: ORD0016 | B17: 45199 | C17: CUST1281 | D17: Priya Kumar | E17: Kolkata | F17: Books | G17: Excel Mastery | H17: 2 | I17: 399 | J17: 25 | K17: 199.5 | L17: 598.5 | M17: 115.26 | N17: Credit Card | O17: Cancelled | P17: =IF(L17>20000,"High Value","Low Value") -> Low Value | Q17: =IF(L17>50000,"Premium",IF(L17>20000,"High",IF(L17>5000,"Medium","Low"))) -> Low | R17: {=_xlfn.IFS(L17>50000,"Premium",L17>20000,"High",L17>5000,"Medium",TRUE,"Low")} -> Low
A18: ORD0017 | B18: 45280 | C18: CUST1332 | D18: Pooja Das | E18: Ahmedabad | F18: Clothing | G18: Shoes | H18: 3 | I18: 2499 | J18: 15 | K18: 1124.55 | L18: 6372.45 | M18: 2221.08 | N18: UPI | O18: Delivered | P18: =IF(L18>20000,"High Value","Low Value") -> Low Value | Q18: =IF(L18>50000,"Premium",IF(L18>20000,"High",IF(L18>5000,"Medium","Low"))) -> Medium | R18: {=_xlfn.IFS(L18>50000,"Premium",L18>20000,"High",L18>5000,"Medium",TRUE,"Low")} -> Medium
A19: ORD0018 | B19: 45042 | C19: CUST1301 | D19: Sneha Sharma | E19: Mumbai | F19: Electronics | G19: Earbuds | H19: 1 | I19: 3500 | J19: 20 | K19: 700 | L19: 2800 | M19: 605.29 | N19: UPI | O19: Delivered | P19: =IF(L19>20000,"High Value","Low Value") -> Low Value | Q19: =IF(L19>50000,"Premium",IF(L19>20000,"High",IF(L19>5000,"Medium","Low"))) -> Low | R19: {=_xlfn.IFS(L19>50000,"Premium",L19>20000,"High",L19>5000,"Medium",TRUE,"Low")} -> Low
A20: ORD0019 | B20: 44961 | C20: CUST1142 | D20: Kavita Iyer | E20: Delhi | F20: Electronics | G20: Speaker | H20: 3 | I20: 4500 | J20: 0 | K20: 0 | L20: 13500 | M20: 2757.33 | N20: Net Banking | O20: Cancelled | P20: =IF(L20>20000,"High Value","Low Value") -> Low Value | Q20: =IF(L20>50000,"Premium",IF(L20>20000,"High",IF(L20>5000,"Medium","Low"))) -> Medium | R20: {=_xlfn.IFS(L20>50000,"Premium",L20>20000,"High",L20>5000,"Medium",TRUE,"Low")} -> Medium
A21: ORD0020 | B21: 45169 | C21: CUST1049 | D21: Nisha Shah | E21: Kolkata | F21: Clothing | G21: Sneakers | H21: 4 | I21: 3499 | J21: 15 | K21: 2099.4 | L21: 11896.6 | M21: 1274.4 | N21: Cash on Delivery | O21: Returned | P21: =IF(L21>20000,"High Value","Low Value") -> Low Value | Q21: =IF(L21>50000,"Premium",IF(L21>20000,"High",IF(L21>5000,"Medium","Low"))) -> Medium | R21: {=_xlfn.IFS(L21>50000,"Premium",L21>20000,"High",L21>5000,"Medium",TRUE,"Low")} -> Medium
A22: ORD0021 | B22: 44954 | C22: CUST1173 | D22: Diya Singh | E22: Chennai | F22: Beauty | G22: Perfume | H22: 1 | I22: 1800 | J22: 0 | K22: 0 | L22: 1800 | M22: 307.42 | N22: Credit Card | O22: Cancelled | P22: =IF(L22>20000,"High Value","Low Value") -> Low Value | Q22: =IF(L22>50000,"Premium",IF(L22>20000,"High",IF(L22>5000,"Medium","Low"))) -> Low | R22: {=_xlfn.IFS(L22>50000,"Premium",L22>20000,"High",L22>5000,"Medium",TRUE,"Low")} -> Low
A23: ORD0022 | B23: 45156 | C23: CUST1447 | D23: Ananya Das | E23: Mumbai | F23: Clothing | G23: Saree | H23: 2 | I23: 2500 | J23: 10 | K23: 500 | L23: 4500 | M23: 849.55 | N23: UPI | O23: Cancelled | P23: =IF(L23>20000,"High Value","Low Value") -> Low Value | Q23: =IF(L23>50000,"Premium",IF(L23>20000,"High",IF(L23>5000,"Medium","Low"))) -> Low | R23: {=_xlfn.IFS(L23>50000,"Premium",L23>20000,"High",L23>5000,"Medium",TRUE,"Low")} -> Low
A24: ORD0023 | B24: 44934 | C24: CUST1246 | D24: Kiran Mehta | E24: Bangalore | F24: Electronics | G24: Speaker | H24: 2 | I24: 4500 | J24: 5 | K24: 450 | L24: 8550 | M24: 1469.95 | N24: Credit Card | O24: Returned | P24: =IF(L24>20000,"High Value","Low Value") -> Low Value | Q24: =IF(L24>50000,"Premium",IF(L24>20000,"High",IF(L24>5000,"Medium","Low"))) -> Medium | R24: {=_xlfn.IFS(L24>50000,"Premium",L24>20000,"High",L24>5000,"Medium",TRUE,"Low")} -> Medium
A25: ORD0024 | B25: 44928 | C25: CUST1490 | D25: Deepa Bhat | E25: Delhi | F25: Furniture | G25: Bookshelf | H25: 4 | I25: 4200 | J25: 10 | K25: 1680 | L25: 15120 | M25: 2674.76 | N25: Credit Card | O25: Delivered | P25: =IF(L25>20000,"High Value","Low Value") -> Low Value | Q25: =IF(L25>50000,"Premium",IF(L25>20000,"High",IF(L25>5000,"Medium","Low"))) -> Medium | R25: {=_xlfn.IFS(L25>50000,"Premium",L25>20000,"High",L25>5000,"Medium",TRUE,"Low")} -> Medium
... A1001: ORD1000 | B1001: 45013 | C1001: CUST1180 | D1001: Ananya Patel | E1001: Delhi | F1001: Groceries | G1001: Dal (1kg) | H1001: 1 | I1001: 120 | J1001: 10 | K1001: 12 | L1001: 108 | M1001: 24.08 | N1001: Cash on Delivery | O1001: Delivered | P1001: =IF(L1001>20000,"High Value","Low Value") -> Low Value | Q1001: =IF(L1001>50000,"Premium",IF(L1001>20000,"High",IF(L1001>5000,"Medium","Low"))) -> Low | R1001: {=_xlfn.IFS(L1001>50000,"Premium",L1001>20000,"High",L1001>5000,"Medium",TRUE,"Low")} -> Low

Sheet Data validation
A1: Order_ID | B1: Category | C1: Net_Sales | D1: Order_Date
B2: Electronics

Sheet Hard
A1: Category | B1: Net_Sales | C1: Profit | D1: Profit Margin %
A2: Beauty | B2: =VLOOKUP(A2,'Task1 '!A3:C11,2,FALSE) -> 296457.5 | C2: =VLOOKUP(B2,'Task1 '!B3:D11,2,FALSE) -> 0 | D2: =C2/B2 -> 0
A3: Books | B3: =VLOOKUP(A3,'Task1 '!A4:C12,2,FALSE) -> #N/A | C3: =VLOOKUP(B3,'Task1 '!B4:D12,2,FALSE) -> #N/A | D3: =C3/B3 -> #N/A
A4: Clothing | B4: =VLOOKUP(A4,'Task1 '!A5:C13,2,FALSE) -> #N/A | C4: =VLOOKUP(B4,'Task1 '!B5:D13,2,FALSE) -> #N/A | D4: =C4/B4 -> #N/A
A5: Electronics | B5: =VLOOKUP(A5,'Task1 '!A6:C14,2,FALSE) -> #N/A | C5: =VLOOKUP(B5,'Task1 '!B6:D14,2,FALSE) -> #N/A | D5: =C5/B5 -> #N/A
A6: Furniture | B6: =VLOOKUP(A6,'Task1 '!A7:C15,2,FALSE) -> #N/A | C6: =VLOOKUP(B6,'Task1 '!B7:D15,2,FALSE) -> #N/A | D6: =C6/B6 -> #N/A
A7: Groceries | B7: =VLOOKUP(A7,'Task1 '!A8:C16,2,FALSE) -> #N/A | C7: =VLOOKUP(B7,'Task1 '!B8:D16,2,FALSE) -> #N/A | D7: =C7/B7 -> #N/A
A8: Sports | B8: =VLOOKUP(A8,'Task1 '!A9:C17,2,FALSE) -> #N/A | C8: =VLOOKUP(B8,'Task1 '!B9:D17,2,FALSE) -> #N/A | D8: =C8/B8 -> #N/A
